odoo/addons/l10n_es_igic_verifactu_oca/README.rst
odoo/addons/l10n_es_igic_verifactu_oca/__init__.py
odoo/addons/l10n_es_igic_verifactu_oca/__manifest__.py
odoo/addons/l10n_es_igic_verifactu_oca/hooks.py
odoo/addons/l10n_es_igic_verifactu_oca/data/account_fiscal_position_template_canary_data.xml
odoo/addons/l10n_es_igic_verifactu_oca/data/atc_verifactu_map_data.xml
odoo/addons/l10n_es_igic_verifactu_oca/data/atc_verifactu_tax_agency_data.xml
odoo/addons/l10n_es_igic_verifactu_oca/i18n/l10n_es_igic_verifactu_oca.pot
odoo/addons/l10n_es_igic_verifactu_oca/readme/CONTRIBUTORS.rst
odoo/addons/l10n_es_igic_verifactu_oca/readme/DESCRIPTION.rst
odoo/addons/l10n_es_igic_verifactu_oca/readme/USAGE.rst
odoo/addons/l10n_es_igic_verifactu_oca/static/description/icon.png
odoo/addons/l10n_es_igic_verifactu_oca/static/description/index.html
odoo/addons/l10n_es_igic_verifactu_oca/tests/__init__.py
odoo/addons/l10n_es_igic_verifactu_oca/tests/common.py
odoo/addons/l10n_es_igic_verifactu_oca/tests/test_10n_es_igic_verifactu.py
odoo/addons/l10n_es_igic_verifactu_oca/tests/json/verifactu_out_invoice_igic_r_3_igic_r_7_dict.json
odoo/addons/l10n_es_igic_verifactu_oca/tests/json/verifactu_out_refund_igic_r_3_igic_r_3_igic_r_7_dict.json
odoo_addon_l10n_es_igic_verifactu_oca-16.0.1.0.1.dist-info/METADATA
odoo_addon_l10n_es_igic_verifactu_oca-16.0.1.0.1.dist-info/WHEEL
odoo_addon_l10n_es_igic_verifactu_oca-16.0.1.0.1.dist-info/top_level.txt
odoo_addon_l10n_es_igic_verifactu_oca-16.0.1.0.1.dist-info/RECORD
